{
  "date": "2026-06-17",
  "course": "Ascot",
  "minutes_before": 5,
  "generatedAt": "2026-06-17T14:00:23.265Z",
  "races": [
    {
      "race_id": "aaaec054-a6ea-4e4f-865d-a1232aa7288e",
      "race_name": "Queen Mary Stakes (Group 2) (Fillies)",
      "course": "Ascot",
      "off_time": "2026-06-17T13:30:00+00:00",
      "capture_target_time": "2026-06-17T13:25:00.000Z",
      "selected_run_id": "48f6e1b9-5bbb-4333-bd19-53389f19e3a9",
      "selected_run_time": "2026-06-17T13:22:30.886+00:00",
      "selected_run_is_current": true,
      "later_pre_off_run_exists": false,
      "post_off_run_count": 0,
      "pick": {
        "horse_name": "Alta Regina",
        "odds": 5.7,
        "ev": 0.05796467031155483,
        "model_prob": 0.185607836896764,
        "market_prob": 0.17192234508979745,
        "stake": 1,
        "confidence_label": "low"
      },
      "favourite": {
        "horse_name": "Alta Regina",
        "odds": 5.7,
        "ev": 0.05796467031155483,
        "model_prob": 0.185607836896764,
        "market_prob": 0.17192234508979745
      },
      "alternatives": [
        {
          "horse_name": "More Champagne",
          "odds": 11.5,
          "ev": 0.05796467031155483,
          "model_prob": 0.09199692785317869,
          "market_prob": 0.08521368408798657
        },
        {
          "horse_name": "Senorita Bonita",
          "odds": 11.5,
          "ev": 0.05796467031155483,
          "model_prob": 0.09199692785317869,
          "market_prob": 0.08521368408798657
        }
      ],
      "run_quality": "DEGRADED",
      "data_quality_flags": [
        "MISSING_RUNNER_ODDS",
        "NO_TIPSTER_SELECTIONS"
      ],
      "data_quality_short_summary": "DEGRADED — Missing runner odds (26/28 priced), No tipster selections",
      "tipster_short_summary": "No tipster consensus",
      "tipster_alignment_label": "NO_TIPSTER_CONSENSUS",
      "warnings": {
        "noCaptureRun": false,
        "farBeforeCapture": false,
        "laterPreOffRunExists": false,
        "postOffRunsIgnored": false
      }
    },
    {
      "race_id": "00bc2925-9478-48cc-8485-a624c39bae88",
      "race_name": "Queen's Vase (Group 2)",
      "course": "Ascot",
      "off_time": "2026-06-17T14:05:00+00:00",
      "capture_target_time": "2026-06-17T14:00:00.000Z",
      "selected_run_id": "29ee4073-4515-427c-b06e-3dccb5d1b578",
      "selected_run_time": "2026-06-17T13:22:31.474+00:00",
      "selected_run_is_current": false,
      "later_pre_off_run_exists": true,
      "post_off_run_count": 0,
      "pick": {
        "horse_name": "Galiyan",
        "odds": 3.45,
        "ev": 0.027537391069933026,
        "model_prob": 0.29783692494780667,
        "market_prob": 0.28677073819637044,
        "stake": 1,
        "confidence_label": "low"
      },
      "favourite": {
        "horse_name": "Galiyan",
        "odds": 3.45,
        "ev": 0.027537391069933026,
        "model_prob": 0.29783692494780667,
        "market_prob": 0.28677073819637044
      },
      "alternatives": [
        {
          "horse_name": "Asakir",
          "odds": 11.5,
          "ev": 0.027537391069932804,
          "model_prob": 0.08935107748434198,
          "market_prob": 0.08603122145891112
        },
        {
          "horse_name": "Limestone",
          "odds": 5.1,
          "ev": 0.027537391069932804,
          "model_prob": 0.2014779198176339,
          "market_prob": 0.19399196995636825
        }
      ],
      "run_quality": "OK",
      "data_quality_flags": [
        "NO_TIPSTER_SELECTIONS"
      ],
      "data_quality_short_summary": "OK — No tipster selections",
      "tipster_short_summary": "No tipster consensus",
      "tipster_alignment_label": "NO_TIPSTER_CONSENSUS",
      "warnings": {
        "noCaptureRun": false,
        "farBeforeCapture": true,
        "laterPreOffRunExists": true,
        "postOffRunsIgnored": false
      }
    },
    {
      "race_id": "68d27b12-9265-405a-b29b-b1e2f0e9ea05",
      "race_name": "Duke Of Cambridge Stakes (Group 2) (Fillies & Mares)",
      "course": "Ascot",
      "off_time": "2026-06-17T14:40:00+00:00",
      "capture_target_time": "2026-06-17T14:35:00.000Z",
      "selected_run_id": "3582f895-ac2f-442c-881b-2874ee63beb5",
      "selected_run_time": "2026-06-17T14:00:16.153+00:00",
      "selected_run_is_current": true,
      "later_pre_off_run_exists": false,
      "post_off_run_count": 0,
      "pick": {
        "horse_name": "Blue Bolt",
        "odds": 4.1,
        "ev": 0.028084310324475892,
        "model_prob": 0.2507522708108478,
        "market_prob": 0.2389538728693909,
        "stake": 1,
        "confidence_label": "low"
      },
      "favourite": {
        "horse_name": "Blue Bolt",
        "odds": 4.1,
        "ev": 0.028084310324475892,
        "model_prob": 0.2507522708108478,
        "market_prob": 0.2389538728693909
      },
      "alternatives": [
        {
          "horse_name": "Catalina Delcarpio",
          "odds": 8.4,
          "ev": 0.028084310324475892,
          "model_prob": 0.12239098932434236,
          "market_prob": 0.1166322474719646
        },
        {
          "horse_name": "Cathedral",
          "odds": 8.4,
          "ev": 0.028084310324475892,
          "model_prob": 0.12239098932434236,
          "market_prob": 0.1166322474719646
        }
      ],
      "run_quality": "OK",
      "data_quality_flags": [
        "NO_TIPSTER_SELECTIONS"
      ],
      "data_quality_short_summary": "OK — No tipster selections",
      "tipster_short_summary": "No tipster consensus",
      "tipster_alignment_label": "NO_TIPSTER_CONSENSUS",
      "warnings": {
        "noCaptureRun": false,
        "farBeforeCapture": true,
        "laterPreOffRunExists": false,
        "postOffRunsIgnored": false
      }
    },
    {
      "race_id": "d02b3463-b358-45d1-8c0e-96e41123d723",
      "race_name": "Prince Of Wales's Stakes (Group 1)",
      "course": "Ascot",
      "off_time": "2026-06-17T15:20:00+00:00",
      "capture_target_time": "2026-06-17T15:15:00.000Z",
      "selected_run_id": "8bda4cb6-ac86-4a23-b905-69993218a280",
      "selected_run_time": "2026-06-17T14:00:16.673+00:00",
      "selected_run_is_current": true,
      "later_pre_off_run_exists": false,
      "post_off_run_count": 0,
      "pick": {
        "horse_name": "Almaqam",
        "odds": 8.4,
        "ev": 0.009259939975303055,
        "model_prob": 0.12014999285420273,
        "market_prob": 0.11897071062659206,
        "stake": 1,
        "confidence_label": "low"
      },
      "favourite": {
        "horse_name": "Ombudsman",
        "odds": 2.46,
        "ev": 0.009259939975303055,
        "model_prob": 0.4102682682826435,
        "market_prob": 0.40624145092007047
      },
      "alternatives": [
        {
          "horse_name": "Daryz",
          "odds": 3.35,
          "ev": 0.009259939975303055,
          "model_prob": 0.30127162387322476,
          "market_prob": 0.29831461769055917
        },
        {
          "horse_name": "Ombudsman",
          "odds": 2.46,
          "ev": 0.009259939975303055,
          "model_prob": 0.4102682682826435,
          "market_prob": 0.40624145092007047
        }
      ],
      "run_quality": "DEGRADED",
      "data_quality_flags": [
        "MISSING_RUNNER_ODDS",
        "NO_TIPSTER_SELECTIONS"
      ],
      "data_quality_short_summary": "DEGRADED — Missing runner odds (7/8 priced), No tipster selections",
      "tipster_short_summary": "No tipster consensus",
      "tipster_alignment_label": "NO_TIPSTER_CONSENSUS",
      "warnings": {
        "noCaptureRun": false,
        "farBeforeCapture": true,
        "laterPreOffRunExists": false,
        "postOffRunsIgnored": false
      }
    },
    {
      "race_id": "11ef5d60-3ba7-4008-a642-799ca5781b08",
      "race_name": "Royal Hunt Cup (Heritage Handicap)",
      "course": "Ascot",
      "off_time": "2026-06-17T16:00:00+00:00",
      "capture_target_time": "2026-06-17T15:55:00.000Z",
      "selected_run_id": "b3580ce9-56e1-4f15-b6df-dcca006f4b92",
      "selected_run_time": "2026-06-17T14:00:17.169+00:00",
      "selected_run_is_current": true,
      "later_pre_off_run_exists": false,
      "post_off_run_count": 0,
      "pick": {
        "horse_name": "Archivist",
        "odds": 8.4,
        "ev": 0.16514308183176296,
        "model_prob": 0.13870750974187654,
        "market_prob": 0.12040657776432985,
        "stake": 1.694913212280321,
        "confidence_label": "low"
      },
      "favourite": {
        "horse_name": "Archivist",
        "odds": 8.4,
        "ev": 0.16514308183176296,
        "model_prob": 0.13870750974187654,
        "market_prob": 0.12040657776432985
      },
      "alternatives": [
        {
          "horse_name": "Godwinson",
          "odds": 210,
          "ev": -0.009628380443001183,
          "model_prob": 0.004716055331223804,
          "market_prob": 0.004816263110573195
        },
        {
          "horse_name": "Holloway Boy",
          "odds": 34,
          "ev": -0.009628380443001294,
          "model_prob": 0.02912857704579408,
          "market_prob": 0.029747507447657966
        }
      ],
      "run_quality": "DEGRADED",
      "data_quality_flags": [
        "MISSING_RUNNER_ODDS",
        "NO_TIPSTER_SELECTIONS"
      ],
      "data_quality_short_summary": "DEGRADED — Missing runner odds (29/30 priced), No tipster selections",
      "tipster_short_summary": "No tipster consensus",
      "tipster_alignment_label": "NO_TIPSTER_CONSENSUS",
      "warnings": {
        "noCaptureRun": false,
        "farBeforeCapture": true,
        "laterPreOffRunExists": false,
        "postOffRunsIgnored": false
      }
    },
    {
      "race_id": "9b5844d9-69c5-4fcc-9735-7af623f075f7",
      "race_name": "Kensington Palace Stakes (Fillies' Handicap)",
      "course": "Ascot",
      "off_time": "2026-06-17T16:35:00+00:00",
      "capture_target_time": "2026-06-17T16:30:00.000Z",
      "selected_run_id": "ca889230-0941-48b9-a5a2-8e6d22484348",
      "selected_run_time": "2026-06-17T14:00:17.716+00:00",
      "selected_run_is_current": true,
      "later_pre_off_run_exists": false,
      "post_off_run_count": 0,
      "pick": {
        "horse_name": "Stateira",
        "odds": 11,
        "ev": 0.0687263163352938,
        "model_prob": 0.09715693784866307,
        "market_prob": 0.0883330923257911,
        "stake": 1,
        "confidence_label": "low"
      },
      "favourite": {
        "horse_name": "Alobayyah",
        "odds": 5.1,
        "ev": 0.0687263163352938,
        "model_prob": 0.20955417967358703,
        "market_prob": 0.19052235599680437
      },
      "alternatives": [
        {
          "horse_name": "Alobayyah",
          "odds": 5.1,
          "ev": 0.0687263163352938,
          "model_prob": 0.20955417967358703,
          "market_prob": 0.19052235599680437
        },
        {
          "horse_name": "Radiant Beauty",
          "odds": 8.4,
          "ev": 0.06872631633529358,
          "model_prob": 0.12722932337324924,
          "market_prob": 0.11567428756948833
        }
      ],
      "run_quality": "DEGRADED",
      "data_quality_flags": [
        "MISSING_RUNNER_ODDS",
        "NO_TIPSTER_SELECTIONS"
      ],
      "data_quality_short_summary": "DEGRADED — Missing runner odds (24/25 priced), No tipster selections",
      "tipster_short_summary": "No tipster consensus",
      "tipster_alignment_label": "NO_TIPSTER_CONSENSUS",
      "warnings": {
        "noCaptureRun": false,
        "farBeforeCapture": true,
        "laterPreOffRunExists": false,
        "postOffRunsIgnored": false
      }
    },
    {
      "race_id": "677718d7-ccc3-4c56-9144-ed8300d69324",
      "race_name": "Windsor Castle Stakes (Listed Race)",
      "course": "Ascot",
      "off_time": "2026-06-17T17:10:00+00:00",
      "capture_target_time": "2026-06-17T17:05:00.000Z",
      "selected_run_id": "d8b624b5-247e-41a9-ac17-295bc859de90",
      "selected_run_time": "2026-06-17T14:00:18.237+00:00",
      "selected_run_is_current": true,
      "later_pre_off_run_exists": false,
      "post_off_run_count": 0,
      "pick": {
        "horse_name": "Celeron",
        "odds": 11.5,
        "ev": 0.035159475671137086,
        "model_prob": 0.0900138674496641,
        "market_prob": 0.08644308027795572,
        "stake": 1,
        "confidence_label": "low"
      },
      "favourite": {
        "horse_name": "Controlla",
        "odds": 3.45,
        "ev": 0.035159475671137086,
        "model_prob": 0.30004622483221366,
        "market_prob": 0.2881436009265191
      },
      "alternatives": [
        {
          "horse_name": "One Number",
          "odds": 10.5,
          "ev": 0.035159475671137086,
          "model_prob": 0.09858661673058448,
          "market_prob": 0.09467575459014198
        },
        {
          "horse_name": "Sale Shark",
          "odds": 8,
          "ev": 0.035159475671137086,
          "model_prob": 0.12939493445889214,
          "market_prob": 0.12426192789956135
        }
      ],
      "run_quality": "DEGRADED",
      "data_quality_flags": [
        "MISSING_RUNNER_ODDS",
        "NO_TIPSTER_SELECTIONS"
      ],
      "data_quality_short_summary": "DEGRADED — Missing runner odds (23/25 priced), No tipster selections",
      "tipster_short_summary": "No tipster consensus",
      "tipster_alignment_label": "NO_TIPSTER_CONSENSUS",
      "warnings": {
        "noCaptureRun": false,
        "farBeforeCapture": true,
        "laterPreOffRunExists": false,
        "postOffRunsIgnored": false
      }
    }
  ]
}
